some_spark_utils/__init__.py
some_spark_utils/utils.py
some_spark_utils-0.0.1.dist-info/LICENSE
some_spark_utils-0.0.1.dist-info/METADATA
some_spark_utils-0.0.1.dist-info/WHEEL
some_spark_utils-0.0.1.dist-info/top_level.txt
some_spark_utils-0.0.1.dist-info/RECORD
